{
    "keep": {
        "days": false,
        "amount": 7
    },
    "auditLog": "log/.audit.json",
    "files": [
        {
            "date": 1544442391827,
            "name": "log/20181210_winston.log",
            "hash": "8629653618387da74ba0f2a0230aacec"
        },
        {
            "date": 1544442538961,
            "name": "log/20181210_winston.log",
            "hash": "6f9d4b4ebcd45073e881f59a4c3d3b48"
        },
        {
            "date": 1544442603070,
            "name": "log/20181210_winston.log",
            "hash": "660f028d2d431091d74e7dbe2cd54f2e"
        },
        {
            "date": 1544442625578,
            "name": "log/20181210_winston.log",
            "hash": "d3e2d0736250ab1137211254bab7d74d"
        },
        {
            "date": 1544442775571,
            "name": "log/20181210_winston.log",
            "hash": "3fddd9189eaa34a2cbcef6b3c8816bd4"
        },
        {
            "date": 1544442827721,
            "name": "log/20181210_winston.log",
            "hash": "e29cc4eece20be93bb323687994fa7d0"
        },
        {
            "date": 1544443232864,
            "name": "log/20181210_winston.log",
            "hash": "d91cfe315b103e77c7724e573613e927"
        }
    ]
}